findex_common/__init__.py
findex_common/bytes2human.py
findex_common/cfg.py
findex_common/colors.py
findex_common/exceptions.py
findex_common/filetypes.py
findex_common/logo.py
findex_common/nmap.py
findex_common/resourcetypes.py
findex_common/static_variables.py
findex_common/utils.py
findex_common/utils_time.py
findex_common/crawl/__init__.py
findex_common/crawl/crawl.py
findex_common/crawl/files.py
findex_common/crawl/http.py
findex_common-0.5.18.dist-info/DESCRIPTION.rst
findex_common-0.5.18.dist-info/METADATA
findex_common-0.5.18.dist-info/RECORD
findex_common-0.5.18.dist-info/WHEEL
findex_common-0.5.18.dist-info/metadata.json
findex_common-0.5.18.dist-info/top_level.txt
