Metadata-Version: 2.0
Name: findex-common
Version: 0.5.18
Summary: This package contains modules used by different Findex projects.
Home-page: http://github.com/skftn/findex-gui
Author: Sander Ferdinand
Author-email: sa.ferdinand@gmail.com
License: MIT
Platform: UNKNOWN
Classifier: Development Status :: 3 - Alpha
Classifier: Environment :: Console
Classifier: Intended Audience :: Developers
Classifier: License :: OSI Approved :: MIT License
Classifier: Operating System :: POSIX :: Linux
Classifier: Topic :: Software Development :: Libraries :: Python Modules
Classifier: Topic :: Utilities
Classifier: Programming Language :: Python :: 3.5
Requires-Dist: IPy (==0.83)
Requires-Dist: appdirs
Requires-Dist: configparser
Requires-Dist: humanfriendly (==3.2)
Requires-Dist: parse-torrent-name (==1.1.1)
Requires-Dist: python-dateutil
